[
  {
    "Height": 5,
    "Volume": 0.1571
  },
  {
    "Height": 10,
    "Volume": 0.3142
  },
  {
    "Height": 15,
    "Volume": 0.4713
  },
  {
    "Height": 20,
    "Volume": 0.6284
  },
  {
    "Height": 25,
    "Volume": 0.7855
  },
  {
    "Height": 30,
    "Volume": 0.9426
  },
  {
    "Height": 35,
    "Volume": 1.0997
  },
  {
    "Height": 40,
    "Volume": 1.2568
  },
  {
    "Height": 45,
    "Volume": 1.4139
  },
    {
    "Height": 50,
    "Volume": 1.571
  },
  {
    "Height": 55,
    "Volume": 1.7281
  },
  {
    "Height": 60,
    "Volume": 1.8852
  },
  {
    "Height": 65,
    "Volume": 2.0423
  },
  {
    "Height": 70,
    "Volume": 2.1994
  },
  {
    "Height": 75,
    "Volume": 2.3565
  },
  {
    "Height": 80,
    "Volume": 2.5136
  },
  {
    "Height": 85,
    "Volume": 2.6707
  },
  {
    "Height": 90,
    "Volume": 2.8278
  },
  {
    "Height": 95,
    "Volume": 2.9849
  },
  {
    "Height": 100,
    "Volume": 3.142
  }

]